gfse/__init__.py
gfse/app.py
gfse/version.py
gfse/api/__init__.py
gfse/api/error_handler.py
gfse/api/routes.py
gfse/config/swagger.yaml
gunicorn_flask_swagger_example-0.0.2.dist-info/METADATA
gunicorn_flask_swagger_example-0.0.2.dist-info/WHEEL
gunicorn_flask_swagger_example-0.0.2.dist-info/entry_points.txt
gunicorn_flask_swagger_example-0.0.2.dist-info/top_level.txt
gunicorn_flask_swagger_example-0.0.2.dist-info/RECORD
