Metadata-Version: 2.1
Name: gunicorn-flask-swagger-example
Version: 0.0.2
Summary: Simple example using Flask and Swagger powered by gunicorn.
Home-page: https://github.com/danielef/gunicorn-flask-swagger-example
Author: Daniel Estevez
Author-email: daniel.ef@gmail.com
Classifier: Environment :: Console
Classifier: Environment :: MacOS X
Classifier: Intended Audience :: Science/Research
Classifier: Operating System :: POSIX :: Linux
Classifier: Operating System :: MacOS :: MacOS X
Classifier: Programming Language :: Python :: 3.7
Classifier: Programming Language :: Python :: 3.8
Classifier: Programming Language :: Python :: 3.9
Requires-Python: >=3.7
Requires-Dist: colorlog (==6.6.0)
Requires-Dist: flask-cors (==3.0.10)
Requires-Dist: Flask (==2.2.2)
Requires-Dist: gunicorn (==20.1.0)
Requires-Dist: connexion (==2.14.1)
Requires-Dist: swagger-ui-bundle (==0.0.9)
